ooi/__init__.py
ooi/config.py
ooi/exception.py
ooi/log.py
ooi/opts.py
ooi/utils.py
ooi/version.py
ooi/api/__init__.py
ooi/api/base.py
ooi/api/compute.py
ooi/api/helpers.py
ooi/api/helpers_neutron.py
ooi/api/ip_reservation.py
ooi/api/network.py
ooi/api/network_link.py
ooi/api/query.py
ooi/api/securitygroup.py
ooi/api/securitygroup_link.py
ooi/api/storage.py
ooi/api/storage_link.py
ooi/occi/__init__.py
ooi/occi/helpers.py
ooi/occi/validator.py
ooi/occi/core/__init__.py
ooi/occi/core/action.py
ooi/occi/core/attribute.py
ooi/occi/core/category.py
ooi/occi/core/collection.py
ooi/occi/core/entity.py
ooi/occi/core/kind.py
ooi/occi/core/link.py
ooi/occi/core/mixin.py
ooi/occi/core/resource.py
ooi/occi/infrastructure/__init__.py
ooi/occi/infrastructure/compute.py
ooi/occi/infrastructure/contextualization.py
ooi/occi/infrastructure/ip_reservation.py
ooi/occi/infrastructure/network.py
ooi/occi/infrastructure/network_link.py
ooi/occi/infrastructure/securitygroup.py
ooi/occi/infrastructure/securitygroup_link.py
ooi/occi/infrastructure/storage.py
ooi/occi/infrastructure/storage_link.py
ooi/occi/infrastructure/templates.py
ooi/occi/rendering/__init__.py
ooi/occi/rendering/headers.py
ooi/occi/rendering/occi_json.py
ooi/occi/rendering/text.py
ooi/occi/rendering/urilist.py
ooi/openstack/__init__.py
ooi/openstack/contextualization.py
ooi/openstack/helpers.py
ooi/openstack/network.py
ooi/openstack/templates.py
ooi/tests/__init__.py
ooi/tests/base.py
ooi/tests/fakes.py
ooi/tests/fakes_network.py
ooi/tests/functional/__init__.py
ooi/tests/functional/middleware/__init__.py
ooi/tests/functional/middleware/test_compute_controller.py
ooi/tests/functional/middleware/test_ip_reservation_controller.py
ooi/tests/functional/middleware/test_middleware.py
ooi/tests/functional/middleware/test_netinterface_controller.py
ooi/tests/functional/middleware/test_network_controller.py
ooi/tests/functional/middleware/test_query_controller.py
ooi-1.2.0.dist-info/DESCRIPTION.rst
ooi-1.2.0.dist-info/METADATA
ooi-1.2.0.dist-info/RECORD
ooi-1.2.0.dist-info/WHEEL
ooi-1.2.0.dist-info/entry_points.txt
ooi-1.2.0.dist-info/metadata.json
ooi-1.2.0.dist-info/pbr.json
ooi-1.2.0.dist-info/top_level.txt
