Metadata-Version: 2.0
Name: ooi
Version: 1.2.0
Summary: OOI: OpenStack OCCI Interface
Home-page: https://launchpad.net/ooi
Author: Spanish National Research Council - CSIC
Author-email: ooi@lists.launchpad.net
License: Apache-2
Platform: UNKNOWN
Classifier: Intended Audience :: Information Technology
Classifier: Intended Audience :: System Administrators
Classifier: License :: OSI Approved :: Apache Software License
Classifier: Operating System :: POSIX :: Linux
Classifier: Programming Language :: Python
Classifier: Programming Language :: Python :: 2
Classifier: Programming Language :: Python :: 2.7
Classifier: Programming Language :: Python :: 3
Classifier: Programming Language :: Python :: 3.5
Requires-Dist: WebOb
Requires-Dist: enum34
Requires-Dist: oslo.config
Requires-Dist: oslo.log
Requires-Dist: pbr
Requires-Dist: routes
